{
    "0": {
        "cells": [
            0,
            23,
            24,
            34,
            39,
            42,
            44,
            55,
            91,
            108,
            124,
            127,
            146,
            154,
            172,
            179,
            186,
            201,
            213,
            221,
            229,
            234,
            241,
            251,
            259,
            273,
            290,
            297,
            325,
            327,
            332,
            333,
            358,
            374,
            376
        ],
        "vectors": [
            [
                0.796,
                2.5650112628936768,
                0.6107319867202899
            ],
            [
                0.796,
                2.5700113773345947,
                0.6200246596993327
            ],
            [
                0.796,
                2.545010805130005,
                0.6239830665534888
            ],
            [
                0.796,
                2.5950119495391846,
                0.6059179878648072
            ],
            [
                0.796,
                2.6100122928619385,
                0.6233449780897875
            ],
            [
                0.796,
                2.560011148452759,
                0.6416838414788523
            ],
            [
                0.796,
                2.6100122928619385,
                0.6376695518312534
            ],
            [
                0.796,
                2.5850117206573486,
                0.6404154414997516
            ],
            [
                0.796,
                2.5700113773345947,
                0.6279921977859563
            ],
            [
                0.796,
                2.545010805130005,
                0.6055306540998552
            ],
            [
                0.796,
                2.5900118350982666,
                0.616594903723906
            ],
            [
                0.796,
                2.6200125217437744,
                0.6259721561071262
            ],
            [
                0.796,
                2.5750114917755127,
                0.6237090387141233
            ],
            [
                0.796,
                2.545010805130005,
                0.6038031138011654
            ],
            [
                0.796,
                2.555011034011841,
                0.6246777981617943
            ],
            [
                0.796,
                2.5800116062164307,
                0.6447826401919377
            ],
            [
                0.796,
                2.555011034011841,
                0.5961293475299706
            ],
            [
                0.796,
                2.6000120639801025,
                0.6232688244756321
            ],
            [
                0.796,
                2.6000120639801025,
                0.6205822659814919
            ],
            [
                0.796,
                2.5650112628936768,
                0.6154343174253185
            ],
            [
                0.796,
                2.6050121784210205,
                0.6106233190984087
            ],
            [
                0.796,
                2.5800116062164307,
                0.6394749046992516
            ],
            [
                0.796,
                2.5750114917755127,
                0.6181276312958882
            ],
            [
                0.796,
                2.6050121784210205,
                0.6143947348174036
            ],
            [
                0.796,
                2.5850117206573486,
                0.6167188315259988
            ],
            [
                0.796,
                2.6150124073028564,
                0.6173589340094092
            ],
            [
                0.796,
                2.6100122928619385,
                0.6178769259015333
            ],
            [
                0.796,
                2.6150124073028564,
                0.6303394875102132
            ],
            [
                0.796,
                2.6100122928619385,
                0.6159132306983038
            ],
            [
                0.796,
                2.5650112628936768,
                0.6212333071230445
            ],
            [
                0.796,
                2.6150124073028564,
                0.61867529099174
            ],
            [
                0.796,
                2.540010690689087,
                0.6248550031080863
            ],
            [
                0.796,
                2.6150124073028564,
                0.6340292216118105
            ],
            [
                0.796,
                2.6000120639801025,
                0.6090724021283245
            ],
            [
                0.796,
                2.6000120639801025,
                0.628120183671273
            ]
        ],
        "centroid": [
            0.7959999999999997,
            2.5850117206573486,
            0.6214017765693294
        ],
        "variance": [
            1.1093356479670479e-31,
            0.0005800265505968127,
            0.00012379985658871563
        ],
        "std": [
            3.3306690738754696e-16,
            0.02408374037803955,
            0.011126538392002953
        ]
    },
    "1": {
        "cells": [
            1,
            9,
            12,
            33,
            67,
            79,
            94,
            97,
            101,
            212,
            238,
            270,
            276,
            295,
            351,
            353
        ],
        "vectors": [
            [
                0.796,
                2.5750114917755127,
                0.4726910659948201
            ],
            [
                0.796,
                2.530010461807251,
                0.5951177410961638
            ],
            [
                0.796,
                2.4750092029571533,
                0.47913172377907687
            ],
            [
                0.796,
                2.5850117206573486,
                0.5054549435989775
            ],
            [
                0.796,
                2.550010919570923,
                0.5787746611608325
            ],
            [
                0.796,
                2.540010690689087,
                0.5604577640658737
            ],
            [
                0.796,
                2.550010919570923,
                0.5808439625330056
            ],
            [
                0.796,
                2.525010347366333,
                0.5781558562201131
            ],
            [
                0.796,
                2.540010690689087,
                0.5005327219648725
            ],
            [
                0.796,
                2.540010690689087,
                0.5452243941473021
            ],
            [
                0.796,
                2.545010805130005,
                0.531811638785388
            ],
            [
                0.796,
                2.5650112628936768,
                0.5773483573541622
            ],
            [
                0.796,
                2.540010690689087,
                0.5395059722274901
            ],
            [
                0.796,
                2.550010919570923,
                0.5792470619783637
            ],
            [
                0.796,
                2.555011034011841,
                0.5353360422806922
            ],
            [
                0.796,
                2.5650112628936768,
                0.5824228335221042
            ]
        ],
        "centroid": [
            0.7959999999999999,
            2.5456358194351196,
            0.5463785462943272
        ],
        "variance": [
            1.232595164407831e-32,
            0.0005683853927251903,
            0.0014544262521387758
        ],
        "std": [
            1.1102230246251565e-16,
            0.023840834564360164,
            0.038136940781069155
        ]
    },
    "2": {
        "cells": [
            2,
            15,
            48,
            83,
            84,
            89,
            98,
            104,
            161,
            163,
            184,
            192,
            195,
            214,
            281,
            289,
            311,
            318,
            342,
            356
        ],
        "vectors": [
            [
                0.796,
                2.710014581680298,
                0.5409309550181267
            ],
            [
                0.796,
                2.695014238357544,
                0.5429811986766077
            ],
            [
                0.796,
                2.7300150394439697,
                0.5155507809648345
            ],
            [
                0.796,
                2.695014238357544,
                0.5313178539039864
            ],
            [
                0.796,
                2.7400152683258057,
                0.5340634698316955
            ],
            [
                0.796,
                2.7300150394439697,
                0.5168300934218046
            ],
            [
                0.796,
                2.720014810562134,
                0.493826340921645
            ],
            [
                0.796,
                2.715014696121216,
                0.5467457357774878
            ],
            [
                0.796,
                2.7300150394439697,
                0.5220027400347932
            ],
            [
                0.796,
                2.695014238357544,
                0.5339097082979023
            ],
            [
                0.796,
                2.690014123916626,
                0.5346409422379975
            ],
            [
                0.796,
                2.715014696121216,
                0.5072293030256723
            ],
            [
                0.796,
                2.7400152683258057,
                0.5205831743578554
            ],
            [
                0.796,
                2.7250149250030518,
                0.5040126292079665
            ],
            [
                0.796,
                2.7400152683258057,
                0.5276902530689103
            ],
            [
                0.796,
                2.695014238357544,
                0.5390560357502189
            ],
            [
                0.796,
                2.720014810562134,
                0.5232207259095197
            ],
            [
                0.796,
                2.685014009475708,
                0.5307515439013352
            ],
            [
                0.796,
                2.7250149250030518,
                0.5331583403526672
            ],
            [
                0.796,
                2.7300150394439697,
                0.5177975285175687
            ]
        ],
        "centroid": [
            0.7959999999999998,
            2.7162647247314453,
            0.5258149676589297
        ],
        "variance": [
            4.930380657631324e-32,
            0.0003072015620887214,
            0.00018015930439167614
        ],
        "std": [
            2.220446049250313e-16,
            0.01752716640215187,
            0.01342234347614738
        ]
    },
    "3": {
        "cells": [
            3,
            13,
            19,
            31,
            41,
            43,
            47,
            61,
            68,
            74,
            87,
            112,
            117,
            148,
            159,
            160,
            164,
            166,
            169,
            198,
            200,
            211,
            220,
            223,
            225,
            226,
            227,
            228,
            265,
            267,
            268,
            282,
            284,
            298,
            303,
            308,
            317,
            335,
            337,
            346,
            372
        ],
        "vectors": [
            [
                0.796,
                2.6350128650665283,
                0.595108414768443
            ],
            [
                0.796,
                2.6200125217437744,
                0.5893953019411389
            ],
            [
                0.796,
                2.6250126361846924,
                0.5909527393739321
            ],
            [
                0.796,
                2.5700113773345947,
                0.5952115145444355
            ],
            [
                0.796,
                2.5950119495391846,
                0.5959258316085704
            ],
            [
                0.796,
                2.5800116062164307,
                0.5889889932474457
            ],
            [
                0.796,
                2.6000120639801025,
                0.5392904454272867
            ],
            [
                0.796,
                2.6300127506256104,
                0.5657540541483846
            ],
            [
                0.796,
                2.5850117206573486,
                0.6009923097420172
            ],
            [
                0.796,
                2.6050121784210205,
                0.5834523317695992
            ],
            [
                0.796,
                2.6150124073028564,
                0.6028690340665622
            ],
            [
                0.796,
                2.6250126361846924,
                0.5831807678947627
            ],
            [
                0.796,
                2.6250126361846924,
                0.5664873866014983
            ],
            [
                0.796,
                2.6150124073028564,
                0.5699700826454976
            ],
            [
                0.796,
                2.6200125217437744,
                0.5909008579086518
            ],
            [
                0.796,
                2.6050121784210205,
                0.5816586664027199
            ],
            [
                0.796,
                2.6250126361846924,
                0.5877375999260513
            ],
            [
                0.796,
                2.6350128650665283,
                0.6028221030633019
            ],
            [
                0.796,
                2.6300127506256104,
                0.6112293953998863
            ],
            [
                0.796,
                2.6150124073028564,
                0.570364302414745
            ],
            [
                0.796,
                2.6200125217437744,
                0.5835652442285206
            ],
            [
                0.796,
                2.6400129795074463,
                0.5629456891405159
            ],
            [
                0.796,
                2.5850117206573486,
                0.567506872813153
            ],
            [
                0.796,
                2.5850117206573486,
                0.5809490201988167
            ],
            [
                0.796,
                2.6200125217437744,
                0.5554569104809016
            ],
            [
                0.796,
                2.6250126361846924,
                0.6019219781788875
            ],
            [
                0.796,
                2.5800116062164307,
                0.5920282364565056
            ],
            [
                0.796,
                2.6150124073028564,
                0.5864867262988952
            ],
            [
                0.796,
                2.5950119495391846,
                0.578806987844004
            ],
            [
                0.796,
                2.5900118350982666,
                0.5849695687049724
            ],
            [
                0.796,
                2.6300127506256104,
                0.6018668251422242
            ],
            [
                0.796,
                2.6250126361846924,
                0.6110536051892476
            ],
            [
                0.796,
                2.6350128650665283,
                0.594717820600431
            ],
            [
                0.796,
                2.5950119495391846,
                0.53722110969067
            ],
            [
                0.796,
                2.6200125217437744,
                0.6074440673214776
            ],
            [
                0.796,
                2.6150124073028564,
                0.5663089915332394
            ],
            [
                0.796,
                2.5900118350982666,
                0.5812825632612402
            ],
            [
                0.796,
                2.5900118350982666,
                0.5979004297427952
            ],
            [
                0.796,
                2.6350128650665283,
                0.5807001619707521
            ],
            [
                0.796,
                2.6300127506256104,
                0.5997177087052731
            ],
            [
                0.796,
                2.6000120639801025,
                0.5804576550018887
            ]
        ],
        "centroid": [
            0.7959999999999997,
            2.6115976950017417,
            0.5845268367170573
        ],
        "variance": [
            1.1093356479670479e-31,
            0.0003481123059772764,
            0.0002916910686078195
        ],
        "std": [
            3.3306690738754696e-16,
            0.01865776797951128,
            0.01707896567734181
        ]
    },
    "4": {
        "cells": [
            4,
            10,
            16,
            20,
            25,
            28,
            32,
            52,
            53,
            54,
            60,
            69,
            70,
            80,
            81,
            82,
            88,
            90,
            93,
            96,
            102,
            106,
            107,
            110,
            116,
            119,
            123,
            125,
            126,
            143,
            145,
            157,
            162,
            167,
            170,
            171,
            175,
            178,
            180,
            183,
            190,
            191,
            193,
            197,
            202,
            205,
            219,
            231,
            237,
            239,
            240,
            247,
            248,
            254,
            266,
            272,
            275,
            277,
            279,
            280,
            286,
            288,
            293,
            300,
            305,
            306,
            310,
            315,
            319,
            320,
            336,
            341,
            352,
            362,
            365,
            366,
            370,
            375
        ],
        "vectors": [
            [
                0.796,
                3.950042963027954,
                0.7065573588511416
            ],
            [
                0.796,
                3.9250423908233643,
                0.7223371200198746
            ],
            [
                0.796,
                3.9300425052642822,
                0.7150440396014053
            ],
            [
                0.796,
                3.9100420475006104,
                0.7261043087394156
            ],
            [
                0.796,
                3.9350426197052,
                0.7224808507295594
            ],
            [
                0.796,
                3.9350426197052,
                0.7141354593460353
            ],
            [
                0.796,
                3.9150421619415283,
                0.7128740401409889
            ],
            [
                0.796,
                3.945042848587036,
                0.7150192589982818
            ],
            [
                0.796,
                3.9350426197052,
                0.7131585171717586
            ],
            [
                0.796,
                3.955043077468872,
                0.701051918746831
            ],
            [
                0.796,
                3.940042734146118,
                0.7075982312532738
            ],
            [
                0.796,
                3.940042734146118,
                0.7122534827746769
            ],
            [
                0.796,
                3.955043077468872,
                0.7066361042486853
            ],
            [
                0.796,
                3.940042734146118,
                0.6936324766890645
            ],
            [
                0.796,
                3.9150421619415283,
                0.7150433386455448
            ],
            [
                0.796,
                3.945042848587036,
                0.714038424202692
            ],
            [
                0.796,
                3.940042734146118,
                0.7112777803896623
            ],
            [
                0.796,
                3.9200422763824463,
                0.722540656580613
            ],
            [
                0.796,
                3.9250423908233643,
                0.7159549347389106
            ],
            [
                0.796,
                3.950042963027954,
                0.6871374827949941
            ],
            [
                0.796,
                3.9200422763824463,
                0.7215535663853619
            ],
            [
                0.796,
                3.945042848587036,
                0.7223180775812205
            ],
            [
                0.796,
                3.9300425052642822,
                0.6926228056111763
            ],
            [
                0.796,
                3.945042848587036,
                0.7057332945957068
            ],
            [
                0.796,
                3.955043077468872,
                0.7046921005969089
            ],
            [
                0.796,
                3.9350426197052,
                0.701090589725796
            ],
            [
                0.796,
                3.940042734146118,
                0.7265062691402698
            ],
            [
                0.796,
                3.965043306350708,
                0.7094607867751712
            ],
            [
                0.796,
                3.9300425052642822,
                0.7214181049557412
            ],
            [
                0.796,
                3.9350426197052,
                0.7104384642554732
            ],
            [
                0.796,
                3.9350426197052,
                0.6926110476513568
            ],
            [
                0.796,
                3.9200422763824463,
                0.7131570116899556
            ],
            [
                0.796,
                3.9100420475006104,
                0.7140042021845331
            ],
            [
                0.796,
                3.945042848587036,
                0.709605681321152
            ],
            [
                0.796,
                3.945042848587036,
                0.7058989505156548
            ],
            [
                0.796,
                3.940042734146118,
                0.7075982312532738
            ],
            [
                0.796,
                3.9150421619415283,
                0.7187656381372561
            ],
            [
                0.796,
                3.9100420475006104,
                0.7196847869349482
            ],
            [
                0.796,
                3.9350426197052,
                0.7121815749974819
            ],
            [
                0.796,
                3.9300425052642822,
                0.7207021085413591
            ],
            [
                0.796,
                3.9350426197052,
                0.715112401520312
            ],
            [
                0.796,
                3.940042734146118,
                0.7039059278373426
            ],
            [
                0.796,
                3.9200422763824463,
                0.708465189244627
            ],
            [
                0.796,
                3.9350426197052,
                0.7224808507295594
            ],
            [
                0.796,
                3.940042734146118,
                0.718872893345652
            ],
            [
                0.796,
                3.9250423908233643,
                0.7196485460164997
            ],
            [
                0.796,
                3.9050419330596924,
                0.7074418991357179
            ],
            [
                0.796,
                3.96004319190979,
                0.709626974400287
            ],
            [
                0.796,
                3.9150421619415283,
                0.7169943689188185
            ],
            [
                0.796,
                3.945042848587036,
                0.7074528795815676
            ],
            [
                0.796,
                3.9250423908233643,
                0.7149755035098991
            ],
            [
                0.796,
                3.940042734146118,
                0.7178908138208661
            ],
            [
                0.796,
                3.945042848587036,
                0.7120767546115125
            ],
            [
                0.796,
                3.945042848587036,
                0.7076694879584294
            ],
            [
                0.796,
                3.9300425052642822,
                0.7170004098379188
            ],
            [
                0.796,
                3.940042734146118,
                0.718872893345652
            ],
            [
                0.796,
                3.945042848587036,
                0.7272859421303116
            ],
            [
                0.796,
                3.9200422763824463,
                0.723527746775864
            ],
            [
                0.796,
                3.9200422763824463,
                0.7252454792822545
            ],
            [
                0.796,
                3.9350426197052,
                0.7207696662023962
            ],
            [
                0.796,
                3.9200422763824463,
                0.722752236728577
            ],
            [
                0.796,
                3.945042848587036,
                0.6862187453376521
            ],
            [
                0.796,
                3.9350426197052,
                0.6939389964232454
            ],
            [
                0.796,
                3.9350426197052,
                0.7104384642554732
            ],
            [
                0.796,
                3.945042848587036,
                0.7189425981806409
            ],
            [
                0.796,
                3.9300425052642822,
                0.7103705491464941
            ],
            [
                0.796,
                3.940042734146118,
                0.714944575246508
            ],
            [
                0.796,
                3.9250423908233643,
                0.7149755035098991
            ],
            [
                0.796,
                3.9300425052642822,
                0.7197175300563164
            ],
            [
                0.796,
                3.945042848587036,
                0.7086375846397908
            ],
            [
                0.796,
                3.9250423908233643,
                0.7188932284259448
            ],
            [
                0.796,
                3.945042848587036,
                0.7162230712278477
            ],
            [
                0.796,
                3.950042963027954,
                0.7273576311633565
            ],
            [
                0.796,
                3.945042848587036,
                0.6431958249660789
            ],
            [
                0.796,
                3.940042734146118,
                0.7083506732346182
            ],
            [
                0.796,
                3.9300425052642822,
                0.7170004098379188
            ],
            [
                0.796,
                3.9250423908233643,
                0.7198726596549563
            ],
            [
                0.796,
                3.9300425052642822,
                0.7187329515712737
            ]
        ],
        "centroid": [
            0.7959999999999996,
            3.9345938914861436,
            0.7121897299913498
        ],
        "variance": [
            1.9721522630525295e-31,
            0.00015461342190797994,
            0.0001411112705225936
        ],
        "std": [
            4.440892098500626e-16,
            0.012434364555858089,
            0.011879026497259512
        ]
    },
    "5": {
        "cells": [
            5
        ],
        "vectors": [
            [
                0.796,
                6.690105438232422,
                0.2503530985989132
            ]
        ],
        "centroid": [
            0.796,
            6.690105438232422,
            0.2503530985989132
        ],
        "variance": [
            0.0,
            0.0,
            0.0
        ],
        "std": [
            0.0,
            0.0,
            0.0
        ]
    },
    "6": {
        "cells": [
            6,
            7,
            18,
            50,
            118,
            232,
            253,
            363,
            377
        ],
        "vectors": [
            [
                0.796,
                2.510010004043579,
                0.5664950983993716
            ],
            [
                0.796,
                2.500009775161743,
                0.5847720926584291
            ],
            [
                0.796,
                2.4850094318389893,
                0.592861890110803
            ],
            [
                0.796,
                2.4550087451934814,
                0.5597829572106187
            ],
            [
                0.796,
                2.4550087451934814,
                0.5575731426268297
            ],
            [
                0.796,
                2.4800093173980713,
                0.562041961698747
            ],
            [
                0.796,
                2.4850094318389893,
                0.5940348747903914
            ],
            [
                0.796,
                2.500009775161743,
                0.5850437406933462
            ],
            [
                0.796,
                2.4650089740753174,
                0.5465955132649034
            ]
        ],
        "centroid": [
            0.7960000000000002,
            2.4816760222117105,
            0.5721334746059379
        ],
        "variance": [
            1.232595164407831e-32,
            0.00035557183178348676,
            0.00026512267909324725
        ],
        "std": [
            1.1102230246251565e-16,
            0.018856612415370018,
            0.016282588218500375
        ]
    },
    "7": {
        "cells": [
            8,
            29,
            45,
            65,
            77,
            86,
            100,
            128,
            136,
            147,
            207,
            244,
            323,
            338,
            339,
            345,
            348,
            350
        ],
        "vectors": [
            [
                0.796,
                2.7950165271759033,
                0.5450300810171594
            ],
            [
                0.796,
                2.820017099380493,
                0.5051821651454526
            ],
            [
                0.796,
                2.7700159549713135,
                0.5368332068266286
            ],
            [
                0.796,
                2.7550156116485596,
                0.5362537201346915
            ],
            [
                0.796,
                2.7850162982940674,
                0.5975283763350128
            ],
            [
                0.796,
                2.7700159549713135,
                0.5400274121872478
            ],
            [
                0.796,
                2.7350151538848877,
                0.5505010618387101
            ],
            [
                0.796,
                2.8100168704986572,
                0.5332952045253118
            ],
            [
                0.796,
                2.7850162982940674,
                0.6063155583399394
            ],
            [
                0.796,
                2.7600157260894775,
                0.5187503556111307
            ],
            [
                0.796,
                2.840017557144165,
                0.5126922480320542
            ],
            [
                0.796,
                2.820017099380493,
                0.5427641529890754
            ],
            [
                0.796,
                2.7850162982940674,
                0.5282943087295373
            ],
            [
                0.796,
                2.7400152683258057,
                0.5599227926709192
            ],
            [
                0.796,
                2.7650158405303955,
                0.555523908186834
            ],
            [
                0.796,
                2.7700159549713135,
                0.5187464173054956
            ],
            [
                0.796,
                2.7500154972076416,
                0.5648584481540248
            ],
            [
                0.796,
                2.7550156116485596,
                0.5260848201640196
            ]
        ],
        "centroid": [
            0.7959999999999998,
            2.7783494790395102,
            0.5432557910107358
        ],
        "variance": [
            4.930380657631324e-32,
            0.0008139261461918876,
            0.0006764700762914634
        ],
        "std": [
            2.220446049250313e-16,
            0.028529390918697994,
            0.026009038357683725
        ]
    },
    "8": {
        "cells": [
            11,
            22,
            40,
            59,
            63,
            132,
            134,
            149,
            199,
            224,
            233,
            236,
            242,
            246,
            252,
            255,
            285,
            309,
            316,
            349,
            367
        ],
        "vectors": [
            [
                0.796,
                0.7299994826316833,
                0.6071453392256541
            ],
            [
                0.796,
                0.7299994826316833,
                0.6114820916486945
            ],
            [
                0.796,
                0.7299994826316833,
                0.5975081143542496
            ],
            [
                0.796,
                0.7149994969367981,
                0.5926134394430723
            ],
            [
                0.796,
                0.7199994921684265,
                0.5579983486182061
            ],
            [
                0.796,
                0.6849995255470276,
                0.5865092057035984
            ],
            [
                0.796,
                0.7049995064735413,
                0.5929292015100392
            ],
            [
                0.796,
                0.7249994874000549,
                0.603708213333792
            ],
            [
                0.796,
                0.7099995017051697,
                0.5662821329096469
            ],
            [
                0.796,
                0.7349994778633118,
                0.6452671699259945
            ],
            [
                0.796,
                0.7049995064735413,
                0.6019815557315666
            ],
            [
                0.796,
                0.7399994730949402,
                0.602675566657554
            ],
            [
                0.796,
                0.7299994826316833,
                0.6602189121079802
            ],
            [
                0.796,
                0.7049995064735413,
                0.6588616943598954
            ],
            [
                0.796,
                0.6949995160102844,
                0.5291565919479894
            ],
            [
                0.796,
                0.7449994683265686,
                0.5901993459398813
            ],
            [
                0.796,
                0.7099995017051697,
                0.6306178901549495
            ],
            [
                0.796,
                0.7349994778633118,
                0.6557276280842591
            ],
            [
                0.796,
                0.7349994778633118,
                0.5802482072183385
            ],
            [
                0.796,
                0.7399994730949402,
                0.6182602394063831
            ],
            [
                0.796,
                0.7399994730949402,
                0.5861062314377578
            ]
        ],
        "centroid": [
            0.7959999999999999,
            0.7221423472676959,
            0.603595100939024
        ],
        "variance": [
            1.232595164407831e-32,
            0.00026564575182361504,
            0.001064034141230748
        ],
        "std": [
            1.1102230246251565e-16,
            0.01629864263745957,
            0.03261953618969387
        ]
    },
    "9": {
        "cells": [
            14,
            17,
            30,
            37,
            72,
            73,
            75,
            76,
            85,
            92,
            95,
            99,
            111,
            114,
            115,
            120,
            130,
            133,
            139,
            144,
            158,
            173,
            176,
            187,
            189,
            194,
            203,
            209,
            216,
            217,
            222,
            235,
            243,
            256,
            260,
            261,
            274,
            278,
            287,
            302,
            307,
            328,
            329,
            359,
            361
        ],
        "vectors": [
            [
                0.796,
                2.670013666152954,
                0.6136662601593789
            ],
            [
                0.796,
                2.6550133228302,
                0.6114357772488603
            ],
            [
                0.796,
                2.68001389503479,
                0.5643123551745235
            ],
            [
                0.796,
                2.675013780593872,
                0.5921649103388024
            ],
            [
                0.796,
                2.7300150394439697,
                0.5876896269684894
            ],
            [
                0.796,
                2.68001389503479,
                0.5961228216911414
            ],
            [
                0.796,
                2.715014696121216,
                0.5937124218542199
            ],
            [
                0.796,
                2.695014238357544,
                0.5862873658433128
            ],
            [
                0.796,
                2.675013780593872,
                0.5930567925527851
            ],
            [
                0.796,
                2.690014123916626,
                0.5998189243314164
            ],
            [
                0.796,
                2.70501446723938,
                0.5886718350948418
            ],
            [
                0.796,
                2.695014238357544,
                0.5862873658433128
            ],
            [
                0.796,
                2.700014352798462,
                0.6174558814899277
            ],
            [
                0.796,
                2.665013551712036,
                0.6177212327348919
            ],
            [
                0.796,
                2.6550133228302,
                0.607726283092245
            ],
            [
                0.796,
                2.6500132083892822,
                0.5938538395529827
            ],
            [
                0.796,
                2.675013780593872,
                0.6005712215030057
            ],
            [
                0.796,
                2.690014123916626,
                0.5602622397838896
            ],
            [
                0.796,
                2.720014810562134,
                0.5821367800918396
            ],
            [
                0.796,
                2.665013551712036,
                0.5958857678515767
            ],
            [
                0.796,
                2.710014581680298,
                0.5711189711879645
            ],
            [
                0.796,
                2.6450130939483643,
                0.593133831393291
            ],
            [
                0.796,
                2.68001389503479,
                0.5766968142339081
            ],
            [
                0.796,
                2.6500132083892822,
                0.5910193992461442
            ],
            [
                0.796,
                2.665013551712036,
                0.6071616813250695
            ],
            [
                0.796,
                2.700014352798462,
                0.580455858949663
            ],
            [
                0.796,
                2.675013780593872,
                0.5910838327095391
            ],
            [
                0.796,
                2.670013666152954,
                0.5934425280050238
            ],
            [
                0.796,
                2.70501446723938,
                0.6216277032340406
            ],
            [
                0.796,
                2.7300150394439697,
                0.5884715910121298
            ],
            [
                0.796,
                2.7300150394439697,
                0.6202422809796851
            ],
            [
                0.796,
                2.6550133228302,
                0.6191393046339586
            ],
            [
                0.796,
                2.6450130939483643,
                0.5891440570602883
            ],
            [
                0.796,
                2.685014009475708,
                0.5752392851601154
            ],
            [
                0.796,
                2.690014123916626,
                0.5972222522793074
            ],
            [
                0.796,
                2.6550133228302,
                0.6156189943287069
            ],
            [
                0.796,
                2.675013780593872,
                0.589037155515777
            ],
            [
                0.796,
                2.68001389503479,
                0.6208265568159073
            ],
            [
                0.796,
                2.685014009475708,
                0.5928035192195109
            ],
            [
                0.796,
                2.6500132083892822,
                0.6066162607679875
            ],
            [
                0.796,
                2.70501446723938,
                0.5670294882163549
            ],
            [
                0.796,
                2.6450130939483643,
                0.6219077940433015
            ],
            [
                0.796,
                2.6500132083892822,
                0.6058010283634914
            ],
            [
                0.796,
                2.690014123916626,
                0.6096826305416272
            ],
            [
                0.796,
                2.6500132083892822,
                0.5992587665485716
            ]
        ],
        "centroid": [
            0.7959999999999997,
            2.6801250086890325,
            0.5962804730882846
        ],
        "variance": [
            1.1093356479670479e-31,
            0.000588347919160079,
            0.00024855295351737083
        ],
        "std": [
            3.3306690738754696e-16,
            0.024255884217238486,
            0.015765562264548984
        ]
    },
    "10": {
        "cells": [
            21,
            103,
            151,
            313
        ],
        "vectors": [
            [
                0.796,
                2.4100077152252197,
                0.6500538073152491
            ],
            [
                0.796,
                2.3300058841705322,
                0.650310765289173
            ],
            [
                0.796,
                2.395007371902466,
                0.5693373292685447
            ],
            [
                0.796,
                2.4100077152252197,
                0.5925356854745484
            ]
        ],
        "centroid": [
            0.796,
            2.3862571716308594,
            0.6155593968368789
        ],
        "variance": [
            0.0,
            0.0010922374969482007,
            0.0012660231946862379
        ],
        "std": [
            0.0,
            0.03304901658065185,
            0.03558121969081777
        ]
    },
    "11": {
        "cells": [
            26,
            105,
            113,
            137,
            140,
            152,
            188,
            204,
            208,
            250,
            291,
            343,
            354,
            371
        ],
        "vectors": [
            [
                0.796,
                2.670013666152954,
                0.5154962158528109
            ],
            [
                0.796,
                2.6450130939483643,
                0.5400890119675569
            ],
            [
                0.796,
                2.665013551712036,
                0.5280322059592583
            ],
            [
                0.796,
                2.6450130939483643,
                0.5530938665395093
            ],
            [
                0.796,
                2.665013551712036,
                0.5385245971612242
            ],
            [
                0.796,
                2.6350128650665283,
                0.5470879259797098
            ],
            [
                0.796,
                2.665013551712036,
                0.5617562364998192
            ],
            [
                0.796,
                2.6450130939483643,
                0.5129399982722592
            ],
            [
                0.796,
                2.660013437271118,
                0.5569941452238856
            ],
            [
                0.796,
                2.665013551712036,
                0.5556838682021855
            ],
            [
                0.796,
                2.6250126361846924,
                0.5026533004127427
            ],
            [
                0.796,
                2.670013666152954,
                0.5347210940110653
            ],
            [
                0.796,
                2.6500132083892822,
                0.5286687996882995
            ],
            [
                0.796,
                2.6500132083892822,
                0.550883865304787
            ]
        ],
        "centroid": [
            0.796,
            2.6539418697357178,
            0.5376160807910795
        ],
        "variance": [
            0.0,
            0.00017921738731274672,
            0.000306988069265478
        ],
        "std": [
            0.0,
            0.013387209840468877,
            0.017521075003134882
        ]
    },
    "12": {
        "cells": [
            27,
            35,
            71,
            109,
            131,
            153,
            155,
            174,
            182,
            215,
            262,
            299,
            321,
            331,
            334,
            355,
            364
        ],
        "vectors": [
            [
                0.796,
                2.510010004043579,
                0.6083286028522895
            ],
            [
                0.796,
                2.4700090885162354,
                0.6182310334817164
            ],
            [
                0.796,
                2.520010232925415,
                0.6305326248240339
            ],
            [
                0.796,
                2.510010004043579,
                0.6756577908800261
            ],
            [
                0.796,
                2.4850094318389893,
                0.6823643786951674
            ],
            [
                0.796,
                2.510010004043579,
                0.6266776653776718
            ],
            [
                0.796,
                2.525010347366333,
                0.6160686192766899
            ],
            [
                0.796,
                2.530010461807251,
                0.6145334575355123
            ],
            [
                0.796,
                2.515010118484497,
                0.6063203186000067
            ],
            [
                0.796,
                2.4800093173980713,
                0.6330021870392456
            ],
            [
                0.796,
                2.500009775161743,
                0.6258478676049546
            ],
            [
                0.796,
                2.525010347366333,
                0.6061772996446738
            ],
            [
                0.796,
                2.530010461807251,
                0.6159238345730775
            ],
            [
                0.796,
                2.4900095462799072,
                0.6747380347833845
            ],
            [
                0.796,
                2.4750092029571533,
                0.6178149042896747
            ],
            [
                0.796,
                2.4700090885162354,
                0.628403451437153
            ],
            [
                0.796,
                2.515010118484497,
                0.6638944202203849
            ]
        ],
        "centroid": [
            0.7959999999999999,
            2.5035392677082733,
            0.6320303818303332
        ],
        "variance": [
            1.232595164407831e-32,
            0.0004199154153139436,
            0.0006154909662560589
        ],
        "std": [
            1.1102230246251565e-16,
            0.020491837772975453,
            0.02480909039557998
        ]
    },
    "13": {
        "cells": [
            36,
            58,
            142,
            150,
            218,
            258,
            283,
            294,
            304,
            360
        ],
        "vectors": [
            [
                0.796,
                0.7549994587898254,
                0.5534959826141103
            ],
            [
                0.796,
                0.784999430179596,
                0.4943187784820548
            ],
            [
                0.796,
                0.7899994254112244,
                0.5705744187584915
            ],
            [
                0.796,
                0.7399994730949402,
                0.554631294335871
            ],
            [
                0.796,
                0.784999430179596,
                0.5361201221636075
            ],
            [
                0.796,
                0.749999463558197,
                0.5675042200328351
            ],
            [
                0.796,
                0.7649994492530823,
                0.5762144304181037
            ],
            [
                0.796,
                0.7599994540214539,
                0.5744181725407325
            ],
            [
                0.796,
                0.7399994730949402,
                0.5606410642208614
            ],
            [
                0.796,
                0.749999463558197,
                0.5737018699023189
            ]
        ],
        "centroid": [
            0.7960000000000002,
            0.7619994521141052,
            0.5561620353468986
        ],
        "variance": [
            1.232595164407831e-32,
            0.0003159993972781195,
            0.0005635172247184209
        ],
        "std": [
            1.1102230246251565e-16,
            0.01777637188174571,
            0.023738517744762853
        ]
    },
    "14": {
        "cells": [
            38,
            56,
            66,
            314
        ],
        "vectors": [
            [
                0.796,
                4.040044784545898,
                0.267323546401263
            ],
            [
                0.796,
                4.070045471191406,
                0.2669829544191982
            ],
            [
                0.796,
                3.9350426197052,
                0.26761200211152053
            ],
            [
                0.796,
                4.065045356750488,
                0.2559631978896389
            ]
        ],
        "centroid": [
            0.796,
            4.027544558048248,
            0.26447042520540515
        ],
        "variance": [
            0.0,
            0.002981375445255452,
            2.4173881416893486e-05
        ],
        "std": [
            0.0,
            0.05460197290625543,
            0.004916694155313455
        ]
    },
    "15": {
        "cells": [
            46,
            121,
            135,
            138,
            141,
            165,
            296,
            330,
            357
        ],
        "vectors": [
            [
                0.796,
                3.655036211013794,
                0.26922973033905984
            ],
            [
                0.796,
                3.675036668777466,
                0.26920708757929235
            ],
            [
                0.796,
                3.6900370121002197,
                0.2692157996708533
            ],
            [
                0.796,
                3.7100374698638916,
                0.2692002173094503
            ],
            [
                0.796,
                3.64003586769104,
                0.2692555047361161
            ],
            [
                0.796,
                3.7250378131866455,
                0.26883115215946524
            ],
            [
                0.796,
                3.7200376987457275,
                0.2688412747200154
            ],
            [
                0.796,
                3.660036325454712,
                0.2693767905306281
            ],
            [
                0.796,
                3.7250378131866455,
                0.26883115215946524
            ]
        ],
        "centroid": [
            0.7960000000000002,
            3.6889258755577936,
            0.2691098565782606
        ],
        "variance": [
            1.232595164407831e-32,
            0.0009543646735022056,
            4.035202535586888e-08
        ],
        "std": [
            1.1102230246251565e-16,
            0.03089279322920162,
            0.00020087813558441068
        ]
    },
    "16": {
        "cells": [
            49,
            51,
            122,
            257,
            271,
            301,
            324,
            340
        ],
        "vectors": [
            [
                0.796,
                3.840040445327759,
                0.26816068917129665
            ],
            [
                0.796,
                3.800039529800415,
                0.2684973816440619
            ],
            [
                0.796,
                3.785039186477661,
                0.2685524553878475
            ],
            [
                0.796,
                3.7600386142730713,
                0.26884123787685366
            ],
            [
                0.796,
                3.785039186477661,
                0.2685524553878475
            ],
            [
                0.796,
                3.7600386142730713,
                0.26884123787685366
            ],
            [
                0.796,
                3.785039186477661,
                0.2685524553878475
            ],
            [
                0.796,
                3.775038957595825,
                0.26883789671908565
            ]
        ],
        "centroid": [
            0.7960000000000002,
            3.7862892150878906,
            0.26860447618146177
        ],
        "variance": [
            1.232595164407831e-32,
            0.0005734637501859652,
            4.7891498428907926e-08
        ],
        "std": [
            1.1102230246251565e-16,
            0.023947103168984036,
            0.0002188412630856163
        ]
    },
    "17": {
        "cells": [
            57
        ],
        "vectors": [
            [
                0.796,
                1.5399987697601318,
                0.44712198596919306
            ]
        ],
        "centroid": [
            0.796,
            1.5399987697601318,
            0.44712198596919306
        ],
        "variance": [
            0.0,
            0.0,
            0.0
        ],
        "std": [
            0.0,
            0.0,
            0.0
        ]
    },
    "18": {
        "cells": [
            62,
            264,
            312
        ],
        "vectors": [
            [
                0.796,
                3.6050350666046143,
                0.2696881906379412
            ],
            [
                0.796,
                3.5450336933135986,
                0.2702057994318416
            ],
            [
                0.796,
                3.61503529548645,
                0.26969973885780496
            ]
        ],
        "centroid": [
            0.7959999999999999,
            3.588368018468221,
            0.2698645763091959
        ],
        "variance": [
            1.232595164407831e-32,
            0.0009555992979181207,
            5.823883661103565e-08
        ],
        "std": [
            1.1102230246251565e-16,
            0.03091276917259469,
            0.00024132723967889669
        ]
    },
    "19": {
        "cells": [
            64
        ],
        "vectors": [
            [
                0.796,
                4.720060348510742,
                0.2562788438803872
            ]
        ],
        "centroid": [
            0.796,
            4.720060348510742,
            0.2562788438803872
        ],
        "variance": [
            0.0,
            0.0,
            0.0
        ],
        "std": [
            0.0,
            0.0,
            0.0
        ]
    },
    "20": {
        "cells": [
            78
        ],
        "vectors": [
            [
                0.796,
                1.8549984693527222,
                0.6695472064340213
            ]
        ],
        "centroid": [
            0.796,
            1.8549984693527222,
            0.6695472064340213
        ],
        "variance": [
            0.0,
            0.0,
            0.0
        ],
        "std": [
            0.0,
            0.0,
            0.0
        ]
    },
    "21": {
        "cells": [
            129,
            181,
            373
        ],
        "vectors": [
            [
                0.796,
                3.155024766921997,
                0.21593518576918377
            ],
            [
                0.796,
                3.1150238513946533,
                0.34074579898966795
            ],
            [
                0.796,
                3.010021448135376,
                0.2294010109136034
            ]
        ],
        "centroid": [
            0.7959999999999999,
            3.0933566888173423,
            0.2620273318908184
        ],
        "variance": [
            1.232595164407831e-32,
            0.0037390600435982277,
            0.003128519938999678
        ],
        "std": [
            1.1102230246251565e-16,
            0.06114785395742215,
            0.05593317386846269
        ]
    },
    "22": {
        "cells": [
            156,
            185,
            206,
            230,
            245,
            292,
            344,
            369
        ],
        "vectors": [
            [
                0.796,
                2.500009775161743,
                0.27175752205123976
            ],
            [
                0.796,
                2.525010347366333,
                0.3027001533277964
            ],
            [
                0.796,
                2.4350082874298096,
                0.24681828201110817
            ],
            [
                0.796,
                2.4350082874298096,
                0.24681828201110817
            ],
            [
                0.796,
                2.4600088596343994,
                0.30403920231364634
            ],
            [
                0.796,
                2.550010919570923,
                0.19751599922883042
            ],
            [
                0.796,
                2.380007028579712,
                0.24694810936837538
            ],
            [
                0.796,
                2.550010919570923,
                0.24384545088579765
            ]
        ],
        "centroid": [
            0.7960000000000002,
            2.4793843030929565,
            0.25755537514973775
        ],
        "variance": [
            1.232595164407831e-32,
            0.0033341369944395183,
            0.0010670339088685952
        ],
        "std": [
            1.1102230246251565e-16,
            0.0577419864088474,
            0.0326654849783161
        ]
    },
    "23": {
        "cells": [
            168
        ],
        "vectors": [
            [
                0.796,
                0.9799992442131042,
                0.18403242989569554
            ]
        ],
        "centroid": [
            0.796,
            0.9799992442131042,
            0.18403242989569554
        ],
        "variance": [
            0.0,
            0.0,
            0.0
        ],
        "std": [
            0.0,
            0.0,
            0.0
        ]
    },
    "24": {
        "cells": [
            177
        ],
        "vectors": [
            [
                0.796,
                1.589998722076416,
                0.15265005368449863
            ]
        ],
        "centroid": [
            0.796,
            1.589998722076416,
            0.15265005368449863
        ],
        "variance": [
            0.0,
            0.0,
            0.0
        ],
        "std": [
            0.0,
            0.0,
            0.0
        ]
    },
    "25": {
        "cells": [
            196
        ],
        "vectors": [
            [
                0.796,
                3.2400267124176025,
                0.41667849113994165
            ]
        ],
        "centroid": [
            0.796,
            3.2400267124176025,
            0.41667849113994165
        ],
        "variance": [
            0.0,
            0.0,
            0.0
        ],
        "std": [
            0.0,
            0.0,
            0.0
        ]
    },
    "26": {
        "cells": [
            210
        ],
        "vectors": [
            [
                0.796,
                0.6649995446205139,
                0.1407035349286311
            ]
        ],
        "centroid": [
            0.796,
            0.6649995446205139,
            0.1407035349286311
        ],
        "variance": [
            0.0,
            0.0,
            0.0
        ],
        "std": [
            0.0,
            0.0,
            0.0
        ]
    },
    "27": {
        "cells": [
            249
        ],
        "vectors": [
            [
                0.796,
                7.415122032165527,
                0.2824658789339232
            ]
        ],
        "centroid": [
            0.796,
            7.415122032165527,
            0.2824658789339232
        ],
        "variance": [
            0.0,
            0.0,
            0.0
        ],
        "std": [
            0.0,
            0.0,
            0.0
        ]
    },
    "28": {
        "cells": [
            263,
            322,
            347
        ],
        "vectors": [
            [
                0.796,
                2.8950188159942627,
                0.5225405029202644
            ],
            [
                0.796,
                2.9250195026397705,
                0.47429974769569966
            ],
            [
                0.796,
                2.870018243789673,
                0.5044357765388636
            ]
        ],
        "centroid": [
            0.7959999999999999,
            2.896685520807902,
            0.5004253423849426
        ],
        "variance": [
            1.232595164407831e-32,
            0.0005055786983171451,
            0.0003959035351575306
        ],
        "std": [
            1.1102230246251565e-16,
            0.022485077236183672,
            0.019897324824144844
        ]
    },
    "29": {
        "cells": [
            269,
            326
        ],
        "vectors": [
            [
                0.796,
                2.1050007343292236,
                0.5678027241737926
            ],
            [
                0.796,
                2.1500017642974854,
                0.6099908136117973
            ]
        ],
        "centroid": [
            0.796,
            2.1275012493133545,
            0.588896768892795
        ],
        "variance": [
            0.0,
            0.0005062731745510973,
            0.00044495872260727037
        ],
        "std": [
            0.0,
            0.02250051498413086,
            0.021094044719002336
        ]
    },
    "30": {
        "cells": [
            368
        ],
        "vectors": [
            [
                0.796,
                2.205003023147583,
                0.24590017879002637
            ]
        ],
        "centroid": [
            0.796,
            2.205003023147583,
            0.24590017879002637
        ],
        "variance": [
            0.0,
            0.0,
            0.0
        ],
        "std": [
            0.0,
            0.0,
            0.0
        ]
    }
}